zabbixbackup/__init__.py
zabbixbackup/__main__.py
zabbixbackup/archiver.py
zabbixbackup/backup_mysql.py
zabbixbackup/backup_postgre.py
zabbixbackup/parser.py
zabbixbackup/parser_defaults.py
zabbixbackup/parser_post.py
zabbixbackup/rotation.py
zabbixbackup/tables.py
zabbixbackup/tablesraw.py
zabbixbackup/utils.py
zabbixbackup/assets/files
zabbixbackup/assets/zabbix_server.conf
zabbixbackup-0.0.1b8.dist-info/LICENSE
zabbixbackup-0.0.1b8.dist-info/METADATA
zabbixbackup-0.0.1b8.dist-info/WHEEL
zabbixbackup-0.0.1b8.dist-info/top_level.txt
zabbixbackup-0.0.1b8.dist-info/RECORD
