Metadata-Version: 2.1
Name: zabbixbackup
Version: 0.0.1b8
Summary: Zabbix database backup utility for postgres and mysql
Author-email: Giampaolo Eusebi <giampaolo.eusebi@gmail.com>
Project-URL: Homepage, https://www.zabbixbackup.com
Project-URL: Repository, https://github.com/geusebi/zabbixbackup
Project-URL: Issues, https://github.com/geusebi/zabbixbackup/issues
Keywords: zabbix,backup,configuration,postgresql,postgres,psql,mysql
Classifier: Development Status :: 4 - Beta
Classifier: Intended Audience :: Information Technology
Classifier: Intended Audience :: System Administrators
Classifier: Topic :: Database
Classifier: Topic :: System :: Recovery Tools
Classifier: License :: OSI Approved :: BSD License
Classifier: Programming Language :: Python :: 3
Classifier: Programming Language :: Python :: 3.7
Classifier: Programming Language :: Python :: 3.8
Classifier: Programming Language :: Python :: 3.9
Classifier: Programming Language :: Python :: 3.10
Classifier: Programming Language :: Python :: 3 :: Only
Requires-Python: >=3.7
License-File: LICENSE
